bin/__init__.py
bin/process_all.py
bin/process_datasets.py
model_evaluation/__init__.py
model_evaluation/file_handler.py
model_evaluation/metadata.py
model_evaluation/model_metadata.py
model_evaluation/utils.py
model_evaluation/version.py
model_evaluation/plotting/__init__.py
model_evaluation/plotting/plot_meta.py
model_evaluation/plotting/plot_tools.py
model_evaluation/plotting/plotting.py
model_evaluation/products/__init__.py
model_evaluation/products/advance_methods.py
model_evaluation/products/grid_methods.py
model_evaluation/products/model_products.py
model_evaluation/products/observation_products.py
model_evaluation/products/product_resampling.py
model_evaluation/products/tools.py
model_evaluation/statistics/__init__.py
model_evaluation/statistics/statistical_methods.py
tests/__init__.py
tests/e2e/__init__.py
tests/e2e/conftest.py
tests/e2e/process_cf/__init__.py
tests/e2e/process_cf/main.py
tests/e2e/process_cf/tests.py
tests/e2e/process_iwc/__init__.py
tests/e2e/process_iwc/main.py
tests/e2e/process_iwc/tests.py
tests/e2e/process_lwc/__init__.py
tests/e2e/process_lwc/main.py
tests/e2e/process_lwc/tests.py
tests/unit/__init__.py
tests/unit/conftest.py
tests/unit/test_advance_methods.py
tests/unit/test_file_handler.py
tests/unit/test_grid_methods.py
tests/unit/test_model_products.py
tests/unit/test_observation_products.py
tests/unit/test_plot_tools.py
tests/unit/test_plotting.py
tests/unit/test_statistical_methods.py
tests/unit/test_tools.py
cloudnetme-0.1.7.dist-info/LICENSE
cloudnetme-0.1.7.dist-info/METADATA
cloudnetme-0.1.7.dist-info/WHEEL
cloudnetme-0.1.7.dist-info/top_level.txt
cloudnetme-0.1.7.dist-info/RECORD
