Metadata-Version: 2.1
Name: cloudnetme
Version: 0.1.7
Summary: Python package for cloudnet model evaluation processing
Home-page: https://github.com/ACTRIS-cloudnet/model_evaluation
Author: Finnish Meteorological Institute
Author-email: actris-cloudnet@fmi.fi
License: MIT License
Platform: UNKNOWN
Classifier: Development Status :: 4 - Beta
Classifier: Programming Language :: Python :: 3.8
Classifier: License :: OSI Approved :: MIT License
Classifier: Operating System :: OS Independent
Classifier: Intended Audience :: Science/Research
Classifier: Topic :: Scientific/Engineering
Requires-Python: >=3.8
Requires-Dist: cloudnetpy (>=1.25.1)
Requires-Dist: matplotlib (>=3.0.2)
Requires-Dist: netCDF4 (>=1.4.2)
Requires-Dist: numpy (>=1.16)
Requires-Dist: requests (>=2.21)
Requires-Dist: scipy (>=1.2)
